[
  {
    "ids": [ 7407, 7408 ],
    "tables": [
      {
        "name": "Weapons/Armour",
        "weight": 1,
        "items": [
          { "id": 1073, "min": 1, "max": 1, "weight": 35 }, //Adamant platelegs
          { "id": 1319, "min": 1, "max": 1, "weight": 30 }, //Rune 2h sword
          { "id": 1373, "min": 1, "max": 1, "weight": 30 }, //Rune battleaxe
          { "id": 1163, "min": 1, "max": 1, "weight": 20 }, //Rune full helm
          { "id": 1079, "min": 1, "max": 1, "weight": 20 }, //Rune platelegs
          { "id": 4129, "min": 1, "max": 1, "weight": 20 }, //Adamant boots
          { "id": 4153, "min": 1, "max": 1, "weight": 1 }, //Granite maul
          { "id": 4101, "min": 1, "max": 1, "weight": 1 } //Mystic robe top (dark)
        ]
      },
      {
        "name": "Runes/Ammo",
        "weight": 1,
        "items": [
          { "id": 554, "min": 37, "max": 37, "weight": 6 }, //Fire rune
          { "id": 554, "min": 75, "max": 75, "weight": 6 }, //Fire rune
          { "id": 554, "min": 150, "max": 150, "weight": 3 }, //Fire rune
          { "id": 562, "min": 30, "max": 30, "weight": 3 }, //Chaos rune
          { "id": 560, "min": 15, "max": 15, "weight": 1 } //Death rune
        ]
      },
      {
        "name": "Other",
        "weight": 1,
        "items": [
          { "id": 995, "min": 400, "max": 10000, "weight": 3 }, //Coins
          { "id": 445, "min": 10, "max": 20, "weight": 3 }, //Gold ore (noted)
          { "id": 2360, "min": 15, "max": 15, "weight": 3 }, //Mithril bar (noted)
          { "id": 2354, "min": 15, "max": 15, "weight": 3 }, //Steel bar (noted)
          { "id": 2358, "min": 10, "max": 15, "weight": 3 }, //Gold bar (noted)
          { "id": 7937, "min": 150, "max": 150, "weight": 1 }, //Pure essence (noted)
          { "id": 451, "min": 1, "max": 1, "weight": 1 }, //Runite ore
          { "id": 2722, "min": 1, "max": 1, "weight": 1 } //Clue scroll (hard)
        ]
      }
    ]
  }
]